runcommands/__init__.py
runcommands/__main__.py
runcommands/args.py
runcommands/collection.py
runcommands/command.py
runcommands/exc.py
runcommands/result.py
runcommands/run.py
runcommands/runner.py
runcommands/commands/__init__.py
runcommands/commands/copy_file.py
runcommands/commands/git_version.py
runcommands/commands/local.py
runcommands/commands/remote.py
runcommands/commands/sync.py
runcommands/completion/__init__.py
runcommands/completion/bash/runcommands-base-command.rc
runcommands/completion/bash/runcommands.rc
runcommands/util/__init__.py
runcommands/util/data.py
runcommands/util/enums.py
runcommands/util/misc.py
runcommands/util/path.py
runcommands/util/printer.py
runcommands/util/prompt.py
runcommands/util/string.py
runcommands-1.0a72.dist-info/LICENSE
runcommands-1.0a72.dist-info/METADATA
runcommands-1.0a72.dist-info/WHEEL
runcommands-1.0a72.dist-info/entry_points.txt
runcommands-1.0a72.dist-info/top_level.txt
runcommands-1.0a72.dist-info/RECORD
