Metadata-Version: 2.2
Name: runcommands
Version: 1.0a72
Summary: A framework for writing console scripts and running commands
Author-email: Wyatt Baldwin <code@wyattbaldwin.com>
License: MIT
Project-URL: documentation, https://runcommands.readthedocs.io
Project-URL: homepage, https://runcommands.readthedocs.io
Project-URL: repository, https://github.com/wylee/runcommands
Keywords: run,commands,console,scripts,terminal
Requires-Python: >=3.9
License-File: LICENSE
Requires-Dist: rich>=10
Requires-Dist: toml>=0.10
Requires-Dist: com.wyattbaldwin.cached_property>=1.0
